{
  "metadata": {
    "title": "ISOTools - Noticias Diarias",
    "description": "Selección diaria de 3 artículos destacados sobre normas ISO",
    "source": "ISOTools Corporate Blog (isotools.us)",
    "generated_date": "2026-05-29",
    "generated_at": "2026-05-29T09:16:13.301760",
    "next_update": "2026-05-30",
    "total_articles": 3,
    "rotation_type": "daily_random_selection",
    "version": "1.0.0",
    "purpose": "Noticias diarias para sección web",
    "github_raw_example": "https://raw.githubusercontent.com/tu-usuario/tu-repo/main/isotools-daily-news.json",
    "parent_source": "isotools_blog_articles.json",
    "language": "español"
  },
  "configuration": {
    "daily_rotation": true,
    "articles_per_day": 3,
    "selection_method": "true_random_with_timestamp",
    "auto_update": true,
    "github_action_enabled": true,
    "cache_duration_hours": 24,
    "rotation_on_each_execution": true
  },
  "daily_news": [
    {
      "title": "Revista Empresa Excelente mayo 2022",
      "image_url": "https://www.isotools.us/wp-content/uploads/2022/05/plantilla-destacada-post-revista-1.jpg",
      "image_exists": true,
      "text": "REVISTA EMPRESA EXCELENTE En este inicio del mes de junio queremos presentarles la nueva edición de nuestra revista…",
      "news_priority": 1,
      "selected_date": "2026-05-29T09:16:13.301664",
      "rotation_id": "2026-05-29-1"
    },
    {
      "title": "¿Cuánto cuesta la certificación ISO 9001?",
      "image_url": "https://www.isotools.us/wp-content/uploads/2017/01/proyecto-de-implementación-ISO-9001.jpg",
      "image_exists": true,
      "text": "La implementación de la norma ISO 9001 varía en función de factores como el tamaño de la empresa,…",
      "news_priority": 2,
      "selected_date": "2026-05-29T09:16:13.301671",
      "rotation_id": "2026-05-29-2"
    },
    {
      "title": "Corporación Q nuevo Partners de ISOTools en Ecuador",
      "image_url": null,
      "image_exists": false,
      "text": "Corporación Q está formado por un equipo especializado que brinda soluciones integrales y automatizadas a sus clientes en…",
      "news_priority": 3,
      "selected_date": "2026-05-29T09:16:13.301674",
      "rotation_id": "2026-05-29-3"
    }
  ],
  "generation_info": {
    "selected_at": "2026-05-29T09:16:13.301760",
    "next_rotation": "2026-05-30T09:16:13.301760",
    "algorithm": "python_random_sample",
    "total_available_articles": 2915,
    "rotation_guaranteed": true
  }
}