{
  "metadata": {
    "title": "ISOTools - Noticias Diarias",
    "description": "Selección diaria de 3 artículos destacados sobre normas ISO",
    "source": "ISOTools Corporate Blog (isotools.us)",
    "generated_date": "2025-10-31",
    "generated_at": "2025-10-31T08:07:58.705525",
    "next_update": "2025-11-01",
    "total_articles": 3,
    "rotation_type": "daily_random_selection",
    "version": "1.0.0",
    "purpose": "Noticias diarias para sección web",
    "github_raw_example": "https://raw.githubusercontent.com/tu-usuario/tu-repo/main/isotools-daily-news.json",
    "parent_source": "isotools_blog_articles.json",
    "language": "español"
  },
  "configuration": {
    "daily_rotation": true,
    "articles_per_day": 3,
    "selection_method": "true_random_with_timestamp",
    "auto_update": true,
    "github_action_enabled": true,
    "cache_duration_hours": 24,
    "rotation_on_each_execution": true
  },
  "daily_news": [
    {
      "title": "ISOTools – Revista Empresa Excelente diciembre 2017",
      "image_url": "https://www.isotools.us/wp-content/uploads/2018/01/img-post-revista-dic17.jpg",
      "image_exists": true,
      "text": "EMPRESA EXCELENTE Comenzamos el año presentando el último número de la Revista Empresa Excelente del año 2017. Como…",
      "news_priority": 1,
      "selected_date": "2025-10-31T08:07:58.705437",
      "rotation_id": "2025-10-31-1"
    },
    {
      "title": "Sistema de Gestión de Inteligencia Artificial (SGIA): elementos clave según la norma ISO 42001",
      "image_url": "https://www.isotools.us/wp-content/uploads/2025/05/Sistema-de-Gestion-de-Inteligencia-Artificial-SGIA-elementos-clave-segun-la-norma-ISO-42001.jpg",
      "image_exists": true,
      "text": "ISO 42001 es el estándar que con mayor velocidad ha logrado posicionarse en el panorama corporativo en las…",
      "news_priority": 2,
      "selected_date": "2025-10-31T08:07:58.705444",
      "rotation_id": "2025-10-31-2"
    },
    {
      "title": "Estrategias eficientes de gestión de malware con ISO 27001",
      "image_url": "https://www.isotools.us/wp-content/uploads/2023/10/malware-con-ISO-27001.jpg",
      "image_exists": true,
      "text": "En la era digital actual, donde la información y los sistemas informáticos son esenciales para las operaciones comerciales...",
      "news_priority": 3,
      "selected_date": "2025-10-31T08:07:58.705446",
      "rotation_id": "2025-10-31-3"
    }
  ],
  "generation_info": {
    "selected_at": "2025-10-31T08:07:58.705525",
    "next_rotation": "2025-11-01T08:07:58.705525",
    "algorithm": "python_random_sample",
    "total_available_articles": 2915,
    "rotation_guaranteed": true
  }
}